{
  "parent": "minecraft:recipes/root",
  "criteria": {
    "has_the_recipe": {
      "conditions": {
        "recipe": "jobsplus:reinforced_diamond_chestplate"
      },
      "trigger": "minecraft:recipe_unlocked"
    },
    "nether_star": {
      "conditions": {
        "items": [
          {
            "items": [
              "minecraft:nether_star"
            ]
          }
        ]
      },
      "trigger": "minecraft:inventory_changed"
    }
  },
  "requirements": [
    [
      "nether_star",
      "has_the_recipe"
    ]
  ],
  "rewards": {
    "recipes": [
      "jobsplus:reinforced_diamond_chestplate"
    ]
  }
}